{
  "web": {
    "client_id": "185180990462-v4qm2svlbnubim8ria9kh0uogfngpc6v.apps.googleusercontent.com",
    "project_id": "lmi-newsletter",
    "auth_uri": "https://accounts.google.com/o/oauth2/auth",
    "token_uri": "https://oauth2.googleapis.com/token",
    "auth_provider_x509_cert_url": "https://www.googleapis.com/oauth2/v1/certs",
    "client_secret": "DYLWXXntvCyk1n5GLGnXCY21",
    "redirect_uris": [
      "https://louisemisellinteriors.co.uk/newsletter/oauth",
      "http://127.0.0.1:8000/newsletter/oauth"
    ],
    "javascript_origins": [
      "https://louisemisellinteriors.co.uk",
      "http://172.0.0.1:8000"
    ]
  }
}